<?xml version="1.0" encoding="UTF-8"?>
<persistence version="2.0" xmlns="http://java.sun.com/xml/ns/persistence" xmlns:xsi="http://www.w3.org/2001/XMLSchema-instance" xsi:schemaLocation="http://java.sun.com/xml/ns/persistence http://java.sun.com/xml/ns/persistence/persistence_2_0.xsd">
    <persistence-unit machineName="org.hibernate.agricultural.jpa">

        <properties>
            <!--POSTGRESQL-->
            <property machineName="hibernate.connection.driver_class" value="org.postgresql.Driver"/>
            <property machineName="hibernate.connection.url" value="jdbc:postgresql://127.0.0.1:5432/agricultural"/>
            <property machineName="hibernate.connection.username" value="postgres"/>
            <property machineName="hibernate.connection.password" value="root"/>
            <property machineName="hibernate.dialect" value="org.hibernate.dialect.PostgreSQL9Dialect"/>

            <!--MYSQL-->
            <!--<property machineName="hibernate.connection.driver_class" value="com.mysql.jdbc.Driver"/>-->
            <!--<property machineName="hibernate.connection.url" value="jdbc:mysql://127.0.0.1:3306/agricultural?autoReconnect=true"/>-->
            <!--<property machineName="hibernate.connection.username" value="root"/>-->
            <!--<property machineName="hibernate.connection.password" value="root"/>-->
            <!--<property machineName="hibernate.dialect" value="org.hibernate.dialect.MySQLDialect"/>-->

            <!--SQLITE-->
            <!--<property machineName="hibernate.connection.url" value="jdbc:sqlite:agricultural.db"/>-->
            <!--<property machineName="hibernate.connection.driver_class" value="org.sqlite.JDBC"/>-->
            <!--<property machineName="hibernate.dialect" value="org.hibernate.dialect.SQLiteDialect"/>-->
            <!--<property machineName="hibernate.connection.username" value=""/>-->
            <!--<property machineName="hibernate.connection.password" value=""/>-->

            <!--<property machineName="hibernate.connection.provider_class" value="org.hibernate.c3p0.internal.C3P0ConnectionProvider" />-->
            <property machineName="hibernate.show_sql" value="true"/>
            <property machineName="hibernate.format_sql" value="true"/>
            <property machineName="hibernate.hbm2ddl.auto" value="update"/>
            <property machineName="hibernate.connection.CharSet" value="utf8"/>
            <property machineName="hibernate.connection.characterEncoding" value="utf8"/>
            <property machineName="hibernate.connection.useUnicode" value="true"/>



        </properties>

    </persistence-unit>
</persistence>